pynenc_mongo/__init__.py
pynenc_mongo/builder.py
pynenc_mongo/arg_cache/__init__.py
pynenc_mongo/arg_cache/mongo_arg_cache.py
pynenc_mongo/broker/__init__.py
pynenc_mongo/broker/mongo_broker.py
pynenc_mongo/conf/__init__.py
pynenc_mongo/conf/config_arg_cache.py
pynenc_mongo/conf/config_broker.py
pynenc_mongo/conf/config_mongo.py
pynenc_mongo/conf/config_orchestrator.py
pynenc_mongo/conf/config_state_backend.py
pynenc_mongo/conf/config_trigger.py
pynenc_mongo/orchestrator/__init__.py
pynenc_mongo/orchestrator/mongo_orchestrator.py
pynenc_mongo/orchestrator/mongo_orchestrator_collections.py
pynenc_mongo/state_backend/__init__.py
pynenc_mongo/state_backend/mongo_state_backend.py
pynenc_mongo/state_backend/mongo_state_backend_collections.py
pynenc_mongo/trigger/__init__.py
pynenc_mongo/trigger/mongo_trigger.py
pynenc_mongo/trigger/mongo_trigger_collections.py
pynenc_mongo/util/__init__.py
pynenc_mongo/util/mongo_client.py
pynenc_mongo/util/mongo_collections.py
pynenc_mongo-0.1.4.dist-info/METADATA
pynenc_mongo-0.1.4.dist-info/WHEEL
pynenc_mongo-0.1.4.dist-info/entry_points.txt
pynenc_mongo-0.1.4.dist-info/licenses/LICENSE
pynenc_mongo-0.1.4.dist-info/RECORD
