Metadata-Version: 2.4
Name: pynenc-mongo
Version: 0.1.4
Summary: MongoDB plugging for pynenc, a distributed task queue for Python.
Project-URL: Homepage, https://pynenc.org
Project-URL: Documentation, https://docs.pynenc.org/plugins/mongo
Project-URL: Repository, https://github.com/pynenc/pynenc_mongo
Author-email: Luis Diaz <code.luis.diaz@proton.me>
License: MIT License
License-File: LICENSE
Classifier: Development Status :: 3 - Alpha
Classifier: Intended Audience :: Developers
Classifier: License :: OSI Approved :: MIT License
Classifier: Programming Language :: Python :: 3.11
Classifier: Topic :: Software Development :: Libraries :: Python Modules
Classifier: Topic :: System :: Distributed Computing
Requires-Python: <4.0,>=3.11.6
Requires-Dist: pymongo<3.13,>=3.12.2
Requires-Dist: pynenc>=0.1.0rc101.dev109
